LICENSE.md
MANIFEST.in
README.rst
setup.py
ovp_search/__init__.py
ovp_search/admin.py
ovp_search/apps.py
ovp_search/filters.py
ovp_search/helpers.py
ovp_search/search_indexes.py
ovp_search/signals.py
ovp_search/urls.py
ovp_search/views.py
ovp_search.egg-info/PKG-INFO
ovp_search.egg-info/SOURCES.txt
ovp_search.egg-info/dependency_links.txt
ovp_search.egg-info/not-zip-safe
ovp_search.egg-info/requires.txt
ovp_search.egg-info/top_level.txt
ovp_search/__pycache__/__init__.cpython-35.pyc
ovp_search/__pycache__/admin.cpython-35.pyc
ovp_search/__pycache__/apps.cpython-35.pyc
ovp_search/__pycache__/filters.cpython-35.pyc
ovp_search/__pycache__/helpers.cpython-35.pyc
ovp_search/__pycache__/search_indexes.cpython-35.pyc
ovp_search/__pycache__/signals.cpython-35.pyc
ovp_search/__pycache__/urls.cpython-35.pyc
ovp_search/__pycache__/views.cpython-35.pyc
ovp_search/migrations/0001_initial.py
ovp_search/migrations/__init__.py
ovp_search/migrations/__pycache__/0001_initial.cpython-35.pyc
ovp_search/migrations/__pycache__/__init__.cpython-35.pyc
ovp_search/models/__init__.py
ovp_search/models/__pycache__/__init__.cpython-35.pyc
ovp_search/templates/search/indexes/ovp_organizations/organization_text.txt
ovp_search/templates/search/indexes/ovp_projects/project_text.txt
ovp_search/tests/__init__.py
ovp_search/tests/runtests.py
ovp_search/tests/test_execution.py
ovp_search/tests/test_signals.py
ovp_search/tests/test_views.py
ovp_search/tests/__pycache__/__init__.cpython-35.pyc
ovp_search/tests/__pycache__/test_execution.cpython-35.pyc
ovp_search/tests/__pycache__/test_signals.cpython-35.pyc
ovp_search/tests/__pycache__/test_views.cpython-35.pyc