Metadata-Version: 1.1
Name: ovp-search
Version: 1.0.15
Summary: This module has search functionality for ovp projects and nonprofits
Home-page: https://github.com/OpenVolunteeringPlatform/django-ovp-search
Author: Atados
Author-email: arroyo@atados.com.br
License: AGPL
Download-URL: https://github.com/OpenVolunteeringPlatform/django-ovp-search/tarball/1.0.15
Platform: UNKNOWN
